RSA_light_iot/RSA_light_iot.py
RSA_light_iot/__init__.py
RSA_light_iot-1.0.1.dist-info/LICENSE
RSA_light_iot-1.0.1.dist-info/METADATA
RSA_light_iot-1.0.1.dist-info/WHEEL
RSA_light_iot-1.0.1.dist-info/top_level.txt
RSA_light_iot-1.0.1.dist-info/RECORD
