Metadata-Version: 2.1
Name: RSA-light-iot
Version: 1.0.1
Summary: A Python package to implement RSA Lightweight adapted for Public key Cryptography in IoT devices.
Home-page: https://github.com/Defcon27/SITS-Secure-IoT-System
Author: Hemanth Kollipara
Author-email: hemanthkollipara95@gmail.com
License: MIT
Platform: UNKNOWN
Classifier: License :: OSI Approved :: MIT License
Classifier: Programming Language :: Python :: 3
Classifier: Programming Language :: Python :: 3.7
